{"All": {"confirmed": 2478551, "recovered": 1974255, "deaths": 231244, "country": "Mexico", "population": 129163276, "sq_km_area": 1958201, "life_expectancy": "71.5", "elevation_in_meters": "1,111", "continent": "North America", "abbreviation": "MX", "location": "Central America", "iso": 484, "capital_city": "Ciudad de M", "lat": "19.4969", "long": "-99.7233"}, "Aguascalientes": {"lat": "21.8853", "long": "-102.2916", "confirmed": 26695, "recovered": 0, "deaths": 2456, "updated": "2021/06/22 05:21:12+00"}, "Baja California": {"lat": "30.8406", "long": "-115.2838", "confirmed": 50286, "recovered": 0, "deaths": 8649, "updated": "2021/06/22 05:21:12+00"}, "Baja California Sur": {"lat": "26.0444", "long": "-111.6661", "confirmed": 36319, "recovered": 0, "deaths": 1486, "updated": "2021/06/22 05:21:12+00"}, "Campeche": {"lat": "19.8301", "long": "-90.5349", "confirmed": 11099, "recovered": 0, "deaths": 1267, "updated": "2021/06/22 05:21:12+00"}, "Chiapas": {"lat": "16.7569", "long": "-93.1292", "confirmed": 12063, "recovered": 0, "deaths": 1656, "updated": "2021/06/22 05:21:12+00"}, "Chihuahua": {"lat": "28.633", "long": "-106.0691", "confirmed": 57486, "recovered": 0, "deaths": 7493, "updated": "2021/06/22 05:21:12+00"}, "Ciudad de Mexico": {"lat": "19.4326", "long": "-99.1332", "confirmed": 673666, "recovered": 0, "deaths": 34461, "updated": "2021/06/22 05:21:12+00"}, "Coahuila": {"lat": "27.0587", "long": "-101.7068", "confirmed": 69397, "recovered": 0, "deaths": 6376, "updated": "2021/06/22 05:21:12+00"}, "Colima": {"lat": "19.1223", "long": "-104.0072", "confirmed": 12208, "recovered": 0, "deaths": 1210, "updated": "2021/06/22 05:21:12+00"}, "Durango": {"lat": "24.5593", "long": "-104.6588", "confirmed": 34588, "recovered": 0, "deaths": 2495, "updated": "2021/06/22 05:21:12+00"}, "Guanajuato": {"lat": "21.019", "long": "-101.2574", "confirmed": 132655, "recovered": 0, "deaths": 11079, "updated": "2021/06/22 05:21:12+00"}, "Guerrero": {"lat": "17.4392", "long": "-99.5451", "confirmed": 41610, "recovered": 0, "deaths": 4549, "updated": "2021/06/22 05:21:12+00"}, "Hidalgo": {"lat": "20.0911", "long": "-98.7624", "confirmed": 39378, "recovered": 0, "deaths": 6268, "updated": "2021/06/22 05:21:12+00"}, "Jalisco": {"lat": "20.6595", "long": "-103.3494", "confirmed": 88151, "recovered": 0, "deaths": 12607, "updated": "2021/06/22 05:21:12+00"}, "Mexico": {"lat": "19.4969", "long": "-99.7233", "confirmed": 256712, "recovered": 0, "deaths": 37212, "updated": "2021/06/22 05:21:12+00"}, "Michoacan": {"lat": "19.5665", "long": "-101.7068", "confirmed": 49066, "recovered": 0, "deaths": 5941, "updated": "2021/06/22 05:21:12+00"}, "Morelos": {"lat": "18.6813", "long": "-99.1013", "confirmed": 34218, "recovered": 0, "deaths": 3550, "updated": "2021/06/22 05:21:12+00"}, "Nayarit": {"lat": "21.7514", "long": "-104.8455", "confirmed": 12535, "recovered": 0, "deaths": 1868, "updated": "2021/06/22 05:21:12+00"}, "Nuevo Leon": {"lat": "25.5922", "long": "-99.9962", "confirmed": 126088, "recovered": 0, "deaths": 9692, "updated": "2021/06/22 05:21:12+00"}, "Oaxaca": {"lat": "17.0732", "long": "-96.7266", "confirmed": 47969, "recovered": 0, "deaths": 3898, "updated": "2021/06/22 05:21:12+00"}, "Puebla": {"lat": "19.0414", "long": "-98.2063", "confirmed": 85952, "recovered": 0, "deaths": 12173, "updated": "2021/06/22 05:21:12+00"}, "Queretaro": {"lat": "20.5888", "long": "-100.3899", "confirmed": 69570, "recovered": 0, "deaths": 4452, "updated": "2021/06/22 05:21:12+00"}, "Quintana Roo": {"lat": "19.1817", "long": "-88.4791", "confirmed": 30733, "recovered": 0, "deaths": 2946, "updated": "2021/06/22 05:21:12+00"}, "San Luis Potosi": {"lat": "22.1565", "long": "-100.9855", "confirmed": 65045, "recovered": 0, "deaths": 5428, "updated": "2021/06/22 05:21:12+00"}, "Sinaloa": {"lat": "25.1721", "long": "-107.4795", "confirmed": 41039, "recovered": 0, "deaths": 6362, "updated": "2021/06/22 05:21:12+00"}, "Sonora": {"lat": "29.2972", "long": "-110.3309", "confirmed": 77872, "recovered": 0, "deaths": 6739, "updated": "2021/06/22 05:21:12+00"}, "Tabasco": {"lat": "17.8409", "long": "-92.6189", "confirmed": 73707, "recovered": 0, "deaths": 4236, "updated": "2021/06/22 05:21:12+00"}, "Tamaulipas": {"lat": "24.2669", "long": "-98.8363", "confirmed": 63234, "recovered": 0, "deaths": 5170, "updated": "2021/06/22 05:21:12+00"}, "Tlaxcala": {"lat": "19.3139", "long": "-98.2404", "confirmed": 20111, "recovered": 0, "deaths": 2525, "updated": "2021/06/22 05:21:12+00"}, "Unknown": {"lat": "", "long": "", "confirmed": 0, "recovered": 1974255, "deaths": 0, "updated": "2021/06/22 05:21:12+00"}, "Veracruz": {"lat": "19.1738", "long": "-96.1342", "confirmed": 63701, "recovered": 0, "deaths": 10063, "updated": "2021/06/22 05:21:12+00"}, "Yucatan": {"lat": "20.7099", "long": "-89.0943", "confirmed": 44434, "recovered": 0, "deaths": 4105, "updated": "2021/06/22 05:21:12+00"}, "Zacatecas": {"lat": "22.7709", "long": "-102.5832", "confirmed": 30964, "recovered": 0, "deaths": 2832, "updated": "2021/06/22 05:21:12+00"}}